pykvs/__init__.py
pykvs/kvs.py
pykvs/version.py
pykvs-0.0.2.dist-info/METADATA
pykvs-0.0.2.dist-info/WHEEL
pykvs-0.0.2.dist-info/top_level.txt
pykvs-0.0.2.dist-info/RECORD
