Metadata-Version: 2.1
Name: pykvs
Version: 0.0.2
Summary: Python simple key-value store.
Home-page: https://github.com/yutayamazaki/pykvs
Author: Yuta Yamazaki
Author-email: yu.yamazakii@gmail.com
Maintainer: Yuta Yamazaki
Maintainer-email: yu.yamazakii@gmail.com
License: MIT
Keywords: python
Platform: UNKNOWN
